MANIFEST.in
README.md
pyproject.toml
setup.cfg
setup.py
src/LancasterAQ/__init__.py
src/LancasterAQ/__main__.py
src/LancasterAQ.egg-info/PKG-INFO
src/LancasterAQ.egg-info/SOURCES.txt
src/LancasterAQ.egg-info/dependency_links.txt
src/LancasterAQ.egg-info/entry_points.txt
src/LancasterAQ.egg-info/requires.txt
src/LancasterAQ.egg-info/top_level.txt
src/LancasterAQ/data/__init__.py
src/LancasterAQ/data/data_object.py
src/LancasterAQ/data/lancaster.gpickle
src/LancasterAQ/data/processed_data.csv
src/LancasterAQ/readwrite/__init__.py
src/LancasterAQ/readwrite/gpickle.py