Metadata-Version: 2.1
Name: LancasterAQ
Version: 1.0.0
Summary: Python package developed for the Lancaster Air Quality project
Home-page: https://github.com/lgouldsbrough/LancasterAQ
Author: Lily Gouldsbrough
Author-email: l.gouldsbrough@lancaster.ac.uk
License: LICENSE
Platform: UNKNOWN
Classifier: Topic :: Scientific/Engineering
Classifier: Development Status :: 4 - Beta
Classifier: Programming Language :: Python :: 3.9
Classifier: Programming Language :: Python :: 3 :: Only
Requires-Python: >=3.9
Provides-Extra: dev
Provides-Extra: examples
